{"status":"success","data":{"id":39,"seed":{"overworld":"8311079125882946541","nether":"8311079125882946541","theEnd":"8311079125882946541","rng":"580","flags":76},"endsAt":1751241600,"leaderboard":[{"rank":1,"player":{"uuid":"c9a24c79ef67475a9151f29dcb8028d0","nickname":"vuxon","roleType":0,"eloRate":null,"eloRank":null,"country":null},"time":474375,"replayExist":true},{"rank":2,"player":{"uuid":"a8c9d33cd80249f28e6ecacbc12a4e70","nickname":"ActualCat866","roleType":0,"eloRate":1218,"eloRank":1028,"country":null},"time":478866,"replayExist":true},{"rank":3,"player":{"uuid":"f14c8e777a214d2089fa091f2577379f","nickname":"thomawks","roleType":0,"eloRate":null,"eloRank":null,"country":null},"time":485257,"replayExist":true},{"rank":4,"player":{"uuid":"6815c5a68a044377908139aa9c34d336","nickname":"dra_BANANA","roleType":0,"eloRate":1079,"eloRank":2008,"country":"jp"},"time":549707,"replayExist":true},{"rank":5,"player":{"uuid":"976d308b414d45e0879f8746e53eaf5f","nickname":"Extream_","roleType":0,"eloRate":1036,"eloRank":2452,"country":null},"time":557138,"replayExist":true},{"rank":6,"player":{"uuid":"1c1a34d4f3dc4f7899f908656c2778ed","nickname":"cyjen","roleType":0,"eloRate":993,"eloRank":2917,"country":"ph"},"time":590358,"replayExist":true},{"rank":7,"player":{"uuid":"1e8a9e63b4af4063bb251dca1c00901b","nickname":"ItsMrPirate","roleType":0,"eloRate":909,"eloRank":3790,"country":null},"time":649814,"replayExist":true},{"rank":8,"player":{"uuid":"da5e9a656dce4f20b9ff229c668ae0f1","nickname":"UncutSteve","roleType":0,"eloRate":861,"eloRank":4360,"country":null},"time":714515,"replayExist":true},{"rank":9,"player":{"uuid":"64b47a785f214669ac07c7aaf3ed8e41","nickname":"Inbisible","roleType":0,"eloRate":833,"eloRank":4687,"country":null},"time":789592,"replayExist":true},{"rank":10,"player":{"uuid":"f9fff1bbbc634954a114aad9f1e5660a","nickname":"xRino","roleType":0,"eloRate":828,"eloRank":4734,"country":null},"time":907108,"replayExist":true},{"rank":11,"player":{"uuid":"7bf614feba4b4f248f23e45fa76c509b","nickname":"poposor","roleType":0,"eloRate":null,"eloRank":null,"country":null},"time":1238011,"replayExist":true},{"rank":12,"player":{"uuid":"b6a4c438bf5143b49b87832c792c2b11","nickname":"JimmyGG","roleType":0,"eloRate":null,"eloRank":null,"country":null},"time":1614833,"replayExist":true},{"rank":13,"player":{"uuid":"41ca71c4af2547a29aad77534bdf969c","nickname":"inlinefun","roleType":0,"eloRate":null,"eloRank":null,"country":null},"time":1762361,"replayExist":true},{"rank":14,"player":{"uuid":"6b5dd8c19d794ca199187c27e7d7e110","nickname":"dumiturd","roleType":0,"eloRate":823,"eloRank":4794,"country":null},"time":1810004,"replayExist":true}]}}