{"status":"success","data":{"id":92,"seed":{"overworld":"37186905863599257","nether":"37186905863599257","theEnd":"37186905863599257","rng":"37186905863599257","flags":207},"endsAt":1783296000,"leaderboard":[{"rank":1,"player":{"uuid":"82338cd1354f45249be661359a8a79c8","nickname":"mefishy","roleType":0,"eloRate":1165,"eloRank":4020,"country":null},"time":441915,"replayExist":true},{"rank":2,"player":{"uuid":"3249f05f04b1443e849cbf90c6ca3895","nickname":"ShuiYao_CN","roleType":1,"eloRate":619,"eloRank":15189,"country":"cn"},"time":488156,"replayExist":true},{"rank":3,"player":{"uuid":"ea1e4485129647d69208da7d38fdf772","nickname":"HungHung123","roleType":0,"eloRate":1522,"eloRank":679,"country":"vn"},"time":519604,"replayExist":true},{"rank":4,"player":{"uuid":"5f55850f079a4e7ba0a1c5e12834c2c0","nickname":"WhimsicalShrimps","roleType":0,"eloRate":874,"eloRank":10571,"country":null},"time":567460,"replayExist":true},{"rank":5,"player":{"uuid":"2ca5e6421210468e9280625d34dbff6e","nickname":"GoogleMinecraft","roleType":0,"eloRate":657,"eloRank":14281,"country":null},"time":1029548,"replayExist":true},{"rank":6,"player":{"uuid":"bd34632f58ea469d8a1edfc0a5be9165","nickname":"PIRATA3D","roleType":1,"eloRate":618,"eloRank":15219,"country":null},"time":1129100,"replayExist":true},{"rank":7,"player":{"uuid":"64f36c9a537f43b8a91b1e43d3c07bca","nickname":"Inaryn","roleType":0,"eloRate":733,"eloRank":12785,"country":null},"time":1240115,"replayExist":true},{"rank":8,"player":{"uuid":"c748a5b7725e4976af4be98da4dc6885","nickname":"Incognito_Toast","roleType":0,"eloRate":null,"eloRank":null,"country":"ca"},"time":1595249,"replayExist":true}]}}