{"status":"success","data":{"id":76,"seed":{"overworld":"4612748639091401473","nether":"4612748639091401473","theEnd":"4612748639091401473","rng":"4612748639091401473","flags":94},"endsAt":1773619200,"leaderboard":[{"rank":1,"player":{"uuid":"a20541925b5648e1ae88a141ca37911e","nickname":"xiamoys","roleType":0,"eloRate":null,"eloRank":null,"country":"cn"},"time":130796,"replayExist":true},{"rank":2,"player":{"uuid":"a39bc5337b1341ac974a7952efdc9d4b","nickname":"Sapless","roleType":0,"eloRate":1293,"eloRank":1872,"country":null},"time":131237,"replayExist":true},{"rank":3,"player":{"uuid":"43b352a1ae5948e697f76d7032510d24","nickname":"sanzione","roleType":0,"eloRate":1490,"eloRank":773,"country":"cn"},"time":141465,"replayExist":true},{"rank":4,"player":{"uuid":"866babb0a018418ea11fcf6eb7523c38","nickname":"BobT0ad","roleType":0,"eloRate":756,"eloRank":14830,"country":"us"},"time":172181,"replayExist":true},{"rank":5,"player":{"uuid":"8507cf4826da41c7b5ce1f2571257498","nickname":"ItsCap","roleType":1,"eloRate":1569,"eloRank":473,"country":"gb"},"time":181493,"replayExist":true},{"rank":6,"player":{"uuid":"8997e412debd47619aa26ea1d8917813","nickname":"vrsd126","roleType":0,"eloRate":1389,"eloRank":1198,"country":"au"},"time":184514,"replayExist":true},{"rank":7,"player":{"uuid":"0532695f914e4abaad0e04a59ccbd7c7","nickname":"AndyMeow","roleType":0,"eloRate":1326,"eloRank":1568,"country":"us"},"time":186926,"replayExist":true},{"rank":8,"player":{"uuid":"6fbedfe6fbf14495a1b45b98e9f896e5","nickname":"zidouri","roleType":0,"eloRate":1511,"eloRank":672,"country":"kr"},"time":188788,"replayExist":true},{"rank":9,"player":{"uuid":"fcf7f0c1f748422ab10f354354d5de42","nickname":"Redsippycup","roleType":1,"eloRate":1208,"eloRank":2887,"country":"us"},"time":202218,"replayExist":true},{"rank":10,"player":{"uuid":"2b5a0c1f5a034004850de4587b402e9b","nickname":"linecow","roleType":3,"eloRate":951,"eloRank":8402,"country":"kp"},"time":203597,"replayExist":true},{"rank":11,"player":{"uuid":"c5c832d32bc84a4ba0dd9f022cfe971b","nickname":"azby101","roleType":0,"eloRate":807,"eloRank":12939,"country":"ca"},"time":204109,"replayExist":true},{"rank":12,"player":{"uuid":"ff9829fd39a94134876e823baf834531","nickname":"MichalAndru","roleType":0,"eloRate":655,"eloRank":20194,"country":null},"time":205252,"replayExist":true},{"rank":13,"player":{"uuid":"9c406f70356340d1bd7d1a56f4d0835a","nickname":"olivierboys","roleType":1,"eloRate":1210,"eloRank":2850,"country":"ca"},"time":207283,"replayExist":true},{"rank":14,"player":{"uuid":"b06cc7b889984ed084564a119b0edc72","nickname":"qwx_","roleType":1,"eloRate":819,"eloRank":12494,"country":"ee"},"time":211151,"replayExist":true},{"rank":15,"player":{"uuid":"6bcfc6b4efca45d18cd86337db12cb94","nickname":"Piissii","roleType":1,"eloRate":1739,"eloRank":205,"country":"kr"},"time":212093,"replayExist":true},{"rank":16,"player":{"uuid":"917ab123477144daa82cbe6005127961","nickname":"Kunaxe","roleType":1,"eloRate":1343,"eloRank":1447,"country":"us"},"time":213175,"replayExist":true},{"rank":17,"player":{"uuid":"2808d7f14fe44b3886a74e5369493f6c","nickname":"ChaoticGamer0","roleType":0,"eloRate":904,"eloRank":9953,"country":"us"},"time":214310,"replayExist":true},{"rank":18,"player":{"uuid":"161eab4bcea74090bf9511a36f95049e","nickname":"277r","roleType":1,"eloRate":1027,"eloRank":6268,"country":"cc"},"time":216683,"replayExist":true},{"rank":19,"player":{"uuid":"d4df665763af4b44bf559cc83de18569","nickname":"NiteNeil","roleType":0,"eloRate":null,"eloRank":null,"country":"cn"},"time":220554,"replayExist":true},{"rank":20,"player":{"uuid":"32595463683e4d6abf01965163c95169","nickname":"L10N","roleType":0,"eloRate":826,"eloRank":12266,"country":"us"},"time":222056,"replayExist":true},{"rank":21,"player":{"uuid":"886f35e5ab234989a8ea9c69e867aebb","nickname":"Tigerdhs","roleType":0,"eloRate":1020,"eloRank":6447,"country":"au"},"time":223731,"replayExist":true},{"rank":22,"player":{"uuid":"f7e037d5636145b8895ff6596db0c95d","nickname":"KreLLeR","roleType":3,"eloRate":1221,"eloRank":2635,"country":"ee"},"time":227532,"replayExist":true},{"rank":23,"player":{"uuid":"fbbd5455fdd04285ae82d0e1afb866a0","nickname":"NotHenry_o1145","roleType":2,"eloRate":926,"eloRank":9168,"country":"cn"},"time":231113,"replayExist":true},{"rank":24,"player":{"uuid":"cce9fd8f90584a1fa1d9adf2fd0af25e","nickname":"ai6s","roleType":0,"eloRate":null,"eloRank":null,"country":null},"time":232523,"replayExist":true},{"rank":25,"player":{"uuid":"50ca746ca449493cb0b612e13b73d3c3","nickname":"garygaslight","roleType":1,"eloRate":1222,"eloRank":2618,"country":null},"time":234958,"replayExist":true},{"rank":26,"player":{"uuid":"e01a2a382f0340778a784dcb09de88a6","nickname":"MCFrasco","roleType":0,"eloRate":796,"eloRank":13341,"country":"it"},"time":235331,"replayExist":true},{"rank":27,"player":{"uuid":"d80e4adc6dd747238b2b4a4e38432383","nickname":"superturtle183","roleType":0,"eloRate":896,"eloRank":10230,"country":null},"time":243588,"replayExist":true},{"rank":28,"player":{"uuid":"5af34e7e4dbc4678bf032d6019c2aa69","nickname":"That_sunrise","roleType":0,"eloRate":1142,"eloRank":3884,"country":null},"time":243893,"replayExist":true},{"rank":29,"player":{"uuid":"4e1c20c3eeec40139e230a77a9fe0b42","nickname":"_f1shb0wl","roleType":0,"eloRate":1518,"eloRank":612,"country":null},"time":245168,"replayExist":true},{"rank":30,"player":{"uuid":"ef5b392731c7430781b3a2a6c287d4b7","nickname":"scrc","roleType":1,"eloRate":1343,"eloRank":1447,"country":"ca"},"time":251442,"replayExist":true},{"rank":31,"player":{"uuid":"784e855f80e44b8e9999aedf8171a50a","nickname":"_alison","roleType":0,"eloRate":830,"eloRank":12140,"country":null},"time":252182,"replayExist":true},{"rank":32,"player":{"uuid":"db0a6c37415f42ec807b9423e1096861","nickname":"SirTrinket","roleType":1,"eloRate":1213,"eloRank":2780,"country":"us"},"time":262434,"replayExist":true},{"rank":33,"player":{"uuid":"3cf0eef97e0343a39e41feb9fcc940fa","nickname":"Gokais4005","roleType":0,"eloRate":882,"eloRank":10579,"country":null},"time":264130,"replayExist":true},{"rank":34,"player":{"uuid":"65fc541092e94a13afe4fe352f81abb4","nickname":"violet_veil","roleType":3,"eloRate":1214,"eloRank":2760,"country":null},"time":274635,"replayExist":true},{"rank":35,"player":{"uuid":"49d45ea2e4e4460a87967a6a639ceb78","nickname":"Sijmentje_123","roleType":1,"eloRate":1066,"eloRank":5340,"country":"nl"},"time":275352,"replayExist":true},{"rank":36,"player":{"uuid":"8511705bf5d941158e0e677f61998954","nickname":"Hdzfx","roleType":0,"eloRate":419,"eloRank":37003,"country":null},"time":287140,"replayExist":true},{"rank":37,"player":{"uuid":"cdaa52e66cf746ca8826586a23e3451d","nickname":"ShirtlessGuy07","roleType":0,"eloRate":1044,"eloRank":5822,"country":null},"time":292825,"replayExist":true},{"rank":38,"player":{"uuid":"29731e15f2d04fd185ec73e63ea402b1","nickname":"Tosti1","roleType":0,"eloRate":747,"eloRank":15213,"country":"nl"},"time":296117,"replayExist":true},{"rank":39,"player":{"uuid":"30c1b785b2014c57b71516f7cf2577ed","nickname":"LoneWolf6795","roleType":0,"eloRate":791,"eloRank":13501,"country":null},"time":303961,"replayExist":true},{"rank":40,"player":{"uuid":"16c25b18829c4a6c87dbcf751c0d6c21","nickname":"Slick6944","roleType":0,"eloRate":517,"eloRank":30733,"country":null},"time":304639,"replayExist":true},{"rank":41,"player":{"uuid":"cf27e1fb19e746fbaefe67f5f8ad7be1","nickname":"KodaCobblestoner","roleType":0,"eloRate":616,"eloRank":23162,"country":null},"time":305737,"replayExist":true},{"rank":42,"player":{"uuid":"611b35b80df444b099b2fa10c762e208","nickname":"o28c","roleType":0,"eloRate":711,"eloRank":16907,"country":"us"},"time":305775,"replayExist":true},{"rank":43,"player":{"uuid":"49f460ca805040e5932860ce3fc91f26","nickname":"ItsTortle","roleType":0,"eloRate":858,"eloRank":11276,"country":"us"},"time":306100,"replayExist":true},{"rank":44,"player":{"uuid":"26e11c87db3e4cd5b0a4cb5e35ce9d3c","nickname":"MilkyMitch","roleType":0,"eloRate":800,"eloRank":13177,"country":"au"},"time":307878,"replayExist":true},{"rank":45,"player":{"uuid":"1b57467ee51f4c758a618d27e7ecfe7c","nickname":"EpilisonMC","roleType":0,"eloRate":632,"eloRank":21860,"country":"us"},"time":314079,"replayExist":true},{"rank":46,"player":{"uuid":"71205b3f99224bec9dc443412db8a9a8","nickname":"_0DKdepzai","roleType":0,"eloRate":772,"eloRank":14172,"country":"vn"},"time":316010,"replayExist":true},{"rank":47,"player":{"uuid":"4ffedcfeaefd4d50953409630b616974","nickname":"OOOO9999","roleType":0,"eloRate":675,"eloRank":18898,"country":"tw"},"time":317879,"replayExist":true},{"rank":48,"player":{"uuid":"655155ab6abc4229937fc37d6e5e4b40","nickname":"Coasterexplorer","roleType":0,"eloRate":1059,"eloRank":5500,"country":null},"time":318519,"replayExist":true},{"rank":49,"player":{"uuid":"577577c82e694f3faf959d3644bee2d9","nickname":"Smuffus","roleType":1,"eloRate":427,"eloRank":36601,"country":null},"time":322907,"replayExist":true},{"rank":50,"player":{"uuid":"b8a0d23e3bc747d1a468cefe84c49bd7","nickname":"monSiiiii","roleType":0,"eloRate":734,"eloRank":15793,"country":null},"time":324711,"replayExist":true}]}}