{"status":"success","data":{"id":81,"seed":{"overworld":"3089695156792879063","nether":"37547851562685","theEnd":"3089695156792879063","rng":"3089695156792879063","flags":207},"endsAt":1776643200,"leaderboard":[{"rank":1,"player":{"uuid":"a20541925b5648e1ae88a141ca37911e","nickname":"xiamoys","roleType":0,"eloRate":null,"eloRank":null,"country":"cn"},"time":330299,"replayExist":true},{"rank":2,"player":{"uuid":"f256f74216ef4f55a1a707505084f04e","nickname":"sylvsunday","roleType":0,"eloRate":1995,"eloRank":141,"country":"br"},"time":394422,"replayExist":true},{"rank":3,"player":{"uuid":"4a6177d27ce040e8ad6eeac825de80d0","nickname":"DanHasArrived","roleType":1,"eloRate":1636,"eloRank":478,"country":"es"},"time":423689,"replayExist":true},{"rank":4,"player":{"uuid":"9b80d94fb6644a34a600acb95356b17e","nickname":"fox1ebtw","roleType":1,"eloRate":1425,"eloRank":1242,"country":"ru"},"time":442306,"replayExist":true},{"rank":5,"player":{"uuid":"0e79410edc844d198aa03defc3d37282","nickname":"xylophoner","roleType":0,"eloRate":716,"eloRank":18920,"country":"us"},"time":544072,"replayExist":true},{"rank":6,"player":{"uuid":"5d5f029796b545879242b31dd361b732","nickname":"Piedup_","roleType":0,"eloRate":1085,"eloRank":5522,"country":"fi"},"time":546040,"replayExist":true},{"rank":7,"player":{"uuid":"95205abc2dfe469b9f46b859c53ca7b6","nickname":"Bobozaver","roleType":0,"eloRate":918,"eloRank":10576,"country":"bg"},"time":576272,"replayExist":true},{"rank":8,"player":{"uuid":"524619c862694137b0b3829fd430bd04","nickname":"Wedansh","roleType":0,"eloRate":956,"eloRank":9189,"country":"au"},"time":581276,"replayExist":true},{"rank":9,"player":{"uuid":"7c3bdcf19bc4425ab43ca1aedad88961","nickname":"rythh_","roleType":1,"eloRate":897,"eloRank":11497,"country":"kh"},"time":590917,"replayExist":true},{"rank":10,"player":{"uuid":"8c20c9e31c09449b8005914ffb176caa","nickname":"Code_Error_","roleType":0,"eloRate":732,"eloRank":18067,"country":null},"time":601182,"replayExist":true},{"rank":11,"player":{"uuid":"0fbf21903344490782bc710349625550","nickname":"WafflesEatDogs","roleType":0,"eloRate":null,"eloRank":null,"country":null},"time":601842,"replayExist":true},{"rank":12,"player":{"uuid":"e05c21dee5ab497ab2a0c7d0c34a4e29","nickname":"MarioStorm5","roleType":2,"eloRate":1301,"eloRank":2122,"country":"us"},"time":608526,"replayExist":true},{"rank":13,"player":{"uuid":"f572b4562c6f45d9bd8e11f6cee59f4d","nickname":"SnitchMC","roleType":0,"eloRate":1117,"eloRank":4813,"country":"us"},"time":610876,"replayExist":true},{"rank":14,"player":{"uuid":"4ffedcfeaefd4d50953409630b616974","nickname":"OOOO9999","roleType":0,"eloRate":606,"eloRank":27201,"country":"tw"},"time":615607,"replayExist":true},{"rank":15,"player":{"uuid":"0c2283a03abe4403bc43a7bc197cb9fc","nickname":"Boomslang31415","roleType":1,"eloRate":711,"eloRank":19212,"country":"za"},"time":620652,"replayExist":true},{"rank":16,"player":{"uuid":"10f99fe4414e41a7928b2ac6c45a6ad5","nickname":"EpicGamer150","roleType":0,"eloRate":988,"eloRank":8190,"country":"ca"},"time":653857,"replayExist":true},{"rank":17,"player":{"uuid":"9839f14f0ac04cbfb884b7d6027f7c88","nickname":"bugboy1720","roleType":0,"eloRate":1337,"eloRank":null,"country":null},"time":669935,"replayExist":true},{"rank":18,"player":{"uuid":"35173b6092084502b43cf69631baa59a","nickname":"purplish_mc","roleType":0,"eloRate":819,"eloRank":14153,"country":"mx"},"time":691968,"replayExist":true},{"rank":19,"player":{"uuid":"3f06c8a546c64ccba9ed51a5e516c006","nickname":"xXBryceCrispyXx","roleType":0,"eloRate":1311,"eloRank":2012,"country":"us"},"time":715360,"replayExist":true},{"rank":20,"player":{"uuid":"c1f30c8912124d519eb6d16c8fff2a1a","nickname":"Mr_Uberlicious","roleType":0,"eloRate":1082,"eloRank":5587,"country":null},"time":727856,"replayExist":true},{"rank":21,"player":{"uuid":"de978ff34caf4e1c99a39344922a14b3","nickname":"ineedneam","roleType":0,"eloRate":null,"eloRank":null,"country":"us"},"time":728858,"replayExist":true},{"rank":22,"player":{"uuid":"6d3d94fccdcd48d4a9e444e8e0ab02ca","nickname":"CiprianIHML","roleType":0,"eloRate":880,"eloRank":11980,"country":"ro"},"time":739141,"replayExist":true},{"rank":23,"player":{"uuid":"99eb2ffcb4264910ba9f43f8153faa02","nickname":"CGQ_","roleType":0,"eloRate":1300,"eloRank":2134,"country":"us"},"time":765935,"replayExist":true},{"rank":24,"player":{"uuid":"f8f3f68baefc47e5bca5c4ccaff54842","nickname":"Bisectqr","roleType":0,"eloRate":1004,"eloRank":7715,"country":null},"time":769394,"replayExist":true},{"rank":25,"player":{"uuid":"c2849de6dc3341a48753f1b6611cc2fd","nickname":"yunotone","roleType":0,"eloRate":983,"eloRank":8336,"country":"us"},"time":794130,"replayExist":true},{"rank":26,"player":{"uuid":"aad360abe38642e0a150707a76961d30","nickname":"BadKKarma","roleType":0,"eloRate":613,"eloRank":26507,"country":"kp"},"time":795117,"replayExist":true},{"rank":27,"player":{"uuid":"d2a4e4d8004a428491423674f88618a6","nickname":"Autismero","roleType":0,"eloRate":549,"eloRank":32089,"country":"cn"},"time":849407,"replayExist":true},{"rank":28,"player":{"uuid":"44333656c6c94dde95e37e11f4cae8fc","nickname":"jamef","roleType":0,"eloRate":913,"eloRank":10787,"country":"us"},"time":878038,"replayExist":true},{"rank":29,"player":{"uuid":"53f41345ff434cd7ba1fcf76e092b822","nickname":"Fuffys","roleType":0,"eloRate":907,"eloRank":11079,"country":null},"time":896169,"replayExist":true},{"rank":30,"player":{"uuid":"06ac6a5c8b1743669bd59673b8fb90d5","nickname":"XiaoWoniuGG","roleType":0,"eloRate":1088,"eloRank":5449,"country":null},"time":934205,"replayExist":true},{"rank":31,"player":{"uuid":"81607857416d4a2e81ea26597a32a6ba","nickname":"chase_is_cool","roleType":0,"eloRate":675,"eloRank":21472,"country":"us"},"time":1050236,"replayExist":true},{"rank":32,"player":{"uuid":"ba651e8189714748a17aa399aa7c69b0","nickname":"Gameinations214","roleType":0,"eloRate":912,"eloRank":10826,"country":null},"time":1076234,"replayExist":true},{"rank":33,"player":{"uuid":"c8f309f96d7a4c439b9a5dd379160f9f","nickname":"Krome00","roleType":0,"eloRate":612,"eloRank":26599,"country":null},"time":1085336,"replayExist":true},{"rank":34,"player":{"uuid":"1ee9a49fdc31486fb9ad6b6518872f1e","nickname":"SteveShades","roleType":0,"eloRate":782,"eloRank":15728,"country":null},"time":1095128,"replayExist":true},{"rank":35,"player":{"uuid":"b1c38c8b164649228166c56f207a6e1e","nickname":"Glickky","roleType":0,"eloRate":727,"eloRank":18317,"country":"au"},"time":1137263,"replayExist":true},{"rank":36,"player":{"uuid":"681e565a05824cbcaf781646f487f858","nickname":"VrBut","roleType":0,"eloRate":642,"eloRank":23948,"country":null},"time":1155270,"replayExist":true},{"rank":37,"player":{"uuid":"f93defb859a64c25a61be72a49d65fdb","nickname":"_Zenos","roleType":0,"eloRate":611,"eloRank":26690,"country":"us"},"time":1172121,"replayExist":true},{"rank":38,"player":{"uuid":"5c408670fb4e4bd7b35453601c9abe37","nickname":"PurpleMochi","roleType":0,"eloRate":1238,"eloRank":2794,"country":"us"},"time":1177385,"replayExist":true},{"rank":39,"player":{"uuid":"dff1d2f851dd4ee2964fe9c4a2f85ed6","nickname":"ghusts_2nd","roleType":0,"eloRate":null,"eloRank":null,"country":null},"time":1209415,"replayExist":true},{"rank":40,"player":{"uuid":"a8f1cafce0884117ac51b598db309070","nickname":"Jlri","roleType":0,"eloRate":null,"eloRank":null,"country":null},"time":1234735,"replayExist":true},{"rank":41,"player":{"uuid":"765e2dc08a6c411f910a1423e3684575","nickname":"Karmov09","roleType":0,"eloRate":679,"eloRank":21213,"country":null},"time":1244843,"replayExist":true},{"rank":42,"player":{"uuid":"473f09f97e1f46cda4f5a8d9b5878ce7","nickname":"MapleMonkeys","roleType":0,"eloRate":null,"eloRank":null,"country":null},"time":1262837,"replayExist":true},{"rank":43,"player":{"uuid":"e70a305947cd452e8a810a35014e566c","nickname":"littleflyinghack","roleType":0,"eloRate":878,"eloRank":12041,"country":"my"},"time":1274665,"replayExist":true},{"rank":44,"player":{"uuid":"f323ca2fea6a4b0594bebfa9410d45bd","nickname":"WiteAsian","roleType":0,"eloRate":673,"eloRank":21611,"country":null},"time":1311731,"replayExist":true},{"rank":45,"player":{"uuid":"ff34c41e43684cdba1331bd656bc6fa7","nickname":"legofoka","roleType":0,"eloRate":801,"eloRank":14922,"country":null},"time":1329567,"replayExist":true},{"rank":46,"player":{"uuid":"e8d72149bf8c4d2cbecef6147220b02c","nickname":"shaamd","roleType":0,"eloRate":760,"eloRank":16711,"country":null},"time":1334836,"replayExist":true},{"rank":47,"player":{"uuid":"519cf15d6d3e410ca7998a32ba510116","nickname":"wittslayer8","roleType":0,"eloRate":640,"eloRank":24094,"country":null},"time":1403762,"replayExist":true},{"rank":48,"player":{"uuid":"7b84c186fb70463485a0495abc8da735","nickname":"John_TAS","roleType":0,"eloRate":657,"eloRank":22757,"country":null},"time":1439660,"replayExist":true},{"rank":49,"player":{"uuid":"08ddf463ac0646d999e344e0446ce21e","nickname":"WADcatYT","roleType":0,"eloRate":620,"eloRank":25863,"country":"ru"},"time":1533869,"replayExist":true},{"rank":50,"player":{"uuid":"749c0e29e9894112a4b4f0b480fe6d39","nickname":"gui_rsg","roleType":0,"eloRate":678,"eloRank":21282,"country":"cn"},"time":1550017,"replayExist":true}]}}