{"status":"success","data":{"id":44,"seed":{"overworld":"-8021403090971421490","nether":"61858746022508","theEnd":"85738024356204","rng":"-8021403090971421490","flags":78},"endsAt":1754265600,"leaderboard":[{"rank":1,"player":{"uuid":"16db4fd94b934e6789aa63342f09417f","nickname":"TamerMushroom","roleType":1,"eloRate":1381,"eloRank":553,"country":"bz"},"time":370335,"replayExist":true},{"rank":2,"player":{"uuid":"ef9b47b332a24552b626d08df939689f","nickname":"thetruth02","roleType":0,"eloRate":1171,"eloRank":1628,"country":null},"time":488429,"replayExist":true}]}}