{"status":"success","data":{"id":46,"seed":{"overworld":"-3231702809030948625","nether":"-3231702809030948625","theEnd":"-3231702809030948625","rng":"-32317028854875","flags":76},"endsAt":1755475200,"leaderboard":[{"rank":1,"player":{"uuid":"553414a2c89b4d6b8c0ba5bd89284508","nickname":"ulsah1n","roleType":0,"eloRate":2068,"eloRank":22,"country":"tr"},"time":227255,"replayExist":true},{"rank":2,"player":{"uuid":"71c9bd85da3549c28e70e981debcd40e","nickname":"pplazzz","roleType":1,"eloRate":1641,"eloRank":152,"country":"au"},"time":277151,"replayExist":true},{"rank":3,"player":{"uuid":"aaddf95767644f79b4765736eb7d5f78","nickname":"PiguinL","roleType":0,"eloRate":null,"eloRank":null,"country":null},"time":325722,"replayExist":true},{"rank":4,"player":{"uuid":"0c302ac113da46deb653c0e7225a8355","nickname":"Nadoms","roleType":0,"eloRate":1317,"eloRank":834,"country":"gb"},"time":326324,"replayExist":true},{"rank":5,"player":{"uuid":"d7d94bc415404033993defd4109c2017","nickname":"insanity3829","roleType":0,"eloRate":1394,"eloRank":566,"country":"de"},"time":335704,"replayExist":true},{"rank":6,"player":{"uuid":"1fcbe1cb3f0c4f2ca08de535b3992229","nickname":"Henen_","roleType":0,"eloRate":1207,"eloRank":1441,"country":null},"time":340202,"replayExist":true},{"rank":7,"player":{"uuid":"f86c668691ce45a69fda4e9927791427","nickname":"majo24","roleType":0,"eloRate":1066,"eloRank":2759,"country":null},"time":399953,"replayExist":true},{"rank":8,"player":{"uuid":"3a91ef0f51e04eeab6f670900d9eb0b6","nickname":"qinghann","roleType":0,"eloRate":1392,"eloRank":571,"country":"cn"},"time":400493,"replayExist":true},{"rank":9,"player":{"uuid":"1e3b3dabe67b4294b3586c34dcf8a1ce","nickname":"xianyiyi","roleType":1,"eloRate":1356,"eloRank":690,"country":"cn"},"time":413363,"replayExist":true},{"rank":10,"player":{"uuid":"c4c2cf69cfe545628c7c3915e056135b","nickname":"quasar11","roleType":0,"eloRate":1132,"eloRank":2053,"country":null},"time":414510,"replayExist":true},{"rank":11,"player":{"uuid":"a1b8c33e9dd849bd846ef45a550bd7de","nickname":"PF_XaQue","roleType":0,"eloRate":193,"eloRank":9444,"country":null},"time":445991,"replayExist":true},{"rank":12,"player":{"uuid":"0d288f330b3d4ac3ba0b5ac2b574c57b","nickname":"Sprigster","roleType":0,"eloRate":1047,"eloRank":3008,"country":null},"time":473079,"replayExist":true},{"rank":13,"player":{"uuid":"466f60d4ca8a4f51b403075b67c8149d","nickname":"shawson","roleType":0,"eloRate":null,"eloRank":null,"country":"pl"},"time":487417,"replayExist":true},{"rank":14,"player":{"uuid":"3a1c7ce22e0e4bb782dd59fe73323a25","nickname":"GeoideNYT_","roleType":0,"eloRate":null,"eloRank":null,"country":null},"time":537412,"replayExist":true},{"rank":15,"player":{"uuid":"f4bd17a809a84cbd8131f2933777f66e","nickname":"111chennan","roleType":0,"eloRate":915,"eloRank":4855,"country":"cn"},"time":650626,"replayExist":true},{"rank":16,"player":{"uuid":"5cbfeeaa84514606899e7b9d9fa46df4","nickname":"TWsteve05","roleType":0,"eloRate":1135,"eloRank":2018,"country":null},"time":684541,"replayExist":true},{"rank":17,"player":{"uuid":"1bdcf91e9c9743af8750ef34852dad15","nickname":"blazingad","roleType":0,"eloRate":992,"eloRank":3737,"country":"us"},"time":721682,"replayExist":true},{"rank":18,"player":{"uuid":"c20e83f1d05c4ad080fc5c5a7cb4cc5f","nickname":"Khaibot","roleType":0,"eloRate":948,"eloRank":4348,"country":"nz"},"time":724660,"replayExist":true},{"rank":19,"player":{"uuid":"4756e334293542398e5a473ee6780677","nickname":"croakyy_","roleType":0,"eloRate":1003,"eloRank":3597,"country":"us"},"time":826607,"replayExist":true},{"rank":20,"player":{"uuid":"fafde71c87434f939f8577be30be9c69","nickname":"yorritio","roleType":0,"eloRate":771,"eloRank":7144,"country":null},"time":902676,"replayExist":true},{"rank":21,"player":{"uuid":"364cdd5932834f7d9b16eced8a860e3a","nickname":"Jxran","roleType":0,"eloRate":null,"eloRank":null,"country":null},"time":965586,"replayExist":true},{"rank":22,"player":{"uuid":"ea70c2f5d3b0488ab3db6549d967e311","nickname":"Pikachu0542","roleType":2,"eloRate":967,"eloRank":4075,"country":"us"},"time":1195531,"replayExist":true},{"rank":23,"player":{"uuid":"730fb57f0c944d23a8167beca3d629c8","nickname":"moldymaxor","roleType":0,"eloRate":818,"eloRank":6459,"country":null},"time":1343061,"replayExist":true},{"rank":24,"player":{"uuid":"3b07a1206a6542648c23452cbb0ace0d","nickname":"Ksarp10j","roleType":0,"eloRate":543,"eloRank":9028,"country":null},"time":1490642,"replayExist":true},{"rank":25,"player":{"uuid":"0341b5cf8b6342b683639607c1a17c5b","nickname":"Awayie","roleType":0,"eloRate":914,"eloRank":4872,"country":null},"time":1916480,"replayExist":true},{"rank":26,"player":{"uuid":"90c99a04b25943f5826cc3fd2f80aaa7","nickname":"Parthenos11","roleType":0,"eloRate":null,"eloRank":null,"country":null},"time":4148836,"replayExist":false}]}}