{"status":"success","data":{"id":58,"seed":{"overworld":"7831777764582310","nether":"7831777764582310","theEnd":"7831777764582310","rng":"7831777764582310","flags":null},"endsAt":1762732800,"leaderboard":[{"rank":1,"player":{"uuid":"a20541925b5648e1ae88a141ca37911e","nickname":"xiamoys","roleType":0,"eloRate":null,"eloRank":null,"country":"cn"},"time":320433,"replayExist":true},{"rank":2,"player":{"uuid":"77b6cebc87354356aa060eed67751f61","nickname":"Obotron","roleType":1,"eloRate":1745,"eloRank":148,"country":"gb"},"time":395830,"replayExist":true},{"rank":3,"player":{"uuid":"bbd1dbd2f3ed4c43b62fc7572229ee61","nickname":"romuxii","roleType":0,"eloRate":1994,"eloRank":57,"country":"by"},"time":439057,"replayExist":true},{"rank":4,"player":{"uuid":"4e265f7763b54d688ab0b6e5efa7adc1","nickname":"TripleToGapHATER","roleType":1,"eloRate":1372,"eloRank":783,"country":"us"},"time":447706,"replayExist":true},{"rank":5,"player":{"uuid":"971dc57b8fff4d7abfb6999f26d29d24","nickname":"Shangou8","roleType":1,"eloRate":1217,"eloRank":1511,"country":"cn"},"time":457513,"replayExist":true},{"rank":6,"player":{"uuid":"ca8111d067ee4c00949fce6fe5bd3b31","nickname":"Banana_lines","roleType":1,"eloRate":null,"eloRank":null,"country":"cn"},"time":461047,"replayExist":true},{"rank":7,"player":{"uuid":"e0dc3f6a0df449998dca31344e8e5c41","nickname":"Miku1050","roleType":2,"eloRate":null,"eloRank":null,"country":null},"time":478690,"replayExist":true},{"rank":8,"player":{"uuid":"4a4f5bec945f4a6586c6057efdbf4443","nickname":"Asna9921","roleType":1,"eloRate":996,"eloRank":3261,"country":"cn"},"time":479495,"replayExist":true},{"rank":9,"player":{"uuid":"abfa366baf394d1ab6358b91279a3d7e","nickname":"Gon_mcsr","roleType":0,"eloRate":1333,"eloRank":919,"country":"jp"},"time":489773,"replayExist":true},{"rank":10,"player":{"uuid":"874f303df4d94d0183f6481be8937e97","nickname":"L9_SUMASHEDSHI69","roleType":0,"eloRate":769,"eloRank":5013,"country":null},"time":498083,"replayExist":true},{"rank":11,"player":{"uuid":"feec1d5b9c654d18bbbcf1ac06871e86","nickname":"B4uit_","roleType":0,"eloRate":1284,"eloRank":1115,"country":"nl"},"time":509520,"replayExist":true},{"rank":12,"player":{"uuid":"5f3ce43e68ef42129dda13fbfe974a4d","nickname":"ch3tt","roleType":0,"eloRate":1151,"eloRank":1981,"country":"ru"},"time":509973,"replayExist":true},{"rank":13,"player":{"uuid":"6edfe08deb4a4397b9e1b6947689ae85","nickname":"puggoboi","roleType":3,"eloRate":1415,"eloRank":647,"country":"au"},"time":517624,"replayExist":true},{"rank":14,"player":{"uuid":"8d1e53768a0e4c42af9a83b41b05d74d","nickname":"carpick96","roleType":0,"eloRate":null,"eloRank":null,"country":null},"time":520527,"replayExist":true},{"rank":15,"player":{"uuid":"adace8dc3d2246a98f8ca092a956803e","nickname":"Koengamer8","roleType":0,"eloRate":1222,"eloRank":1480,"country":"nl"},"time":534944,"replayExist":true},{"rank":16,"player":{"uuid":"3f7eb0b3764843caa1cd32ef2f8241d8","nickname":"LeftyAce","roleType":1,"eloRate":1320,"eloRank":971,"country":"se"},"time":544895,"replayExist":true},{"rank":17,"player":{"uuid":"a99d27e45cfd4a6bb14517531a178d28","nickname":"Buckletz","roleType":0,"eloRate":934,"eloRank":3773,"country":"gb"},"time":566491,"replayExist":true},{"rank":18,"player":{"uuid":"cc87bdae94a6473b810fc8cb2d5752c3","nickname":"Happypumpkinnn","roleType":1,"eloRate":1122,"eloRank":2201,"country":"nl"},"time":584898,"replayExist":true},{"rank":19,"player":{"uuid":"3f06c8a546c64ccba9ed51a5e516c006","nickname":"xXBryceCrispyXx","roleType":0,"eloRate":1212,"eloRank":1564,"country":"us"},"time":605819,"replayExist":true},{"rank":20,"player":{"uuid":"a3fd896f55114dd384fc5a6e12911396","nickname":"csyalsz","roleType":0,"eloRate":null,"eloRank":null,"country":null},"time":630137,"replayExist":true},{"rank":21,"player":{"uuid":"1990de4bbc724057ab7ecf8e576f2eb4","nickname":"AriaThatKid","roleType":0,"eloRate":1037,"eloRank":2871,"country":"ir"},"time":647964,"replayExist":true},{"rank":22,"player":{"uuid":"f16dbfd22ee24acca8939aadca56ce10","nickname":"Lboe12","roleType":3,"eloRate":930,"eloRank":3805,"country":"us"},"time":668820,"replayExist":true},{"rank":23,"player":{"uuid":"d4df665763af4b44bf559cc83de18569","nickname":"NiteNeil","roleType":0,"eloRate":null,"eloRank":null,"country":null},"time":671144,"replayExist":true},{"rank":24,"player":{"uuid":"9e6f468e1b354a0dbcfa213e5564d9f4","nickname":"Pepified","roleType":0,"eloRate":null,"eloRank":null,"country":null},"time":671404,"replayExist":true},{"rank":25,"player":{"uuid":"2e043333dc274c6faca50d4cb820a751","nickname":"Rainy330","roleType":1,"eloRate":1179,"eloRank":1781,"country":"cn"},"time":679264,"replayExist":true},{"rank":26,"player":{"uuid":"3a1c7ce22e0e4bb782dd59fe73323a25","nickname":"GeoideNYT_","roleType":0,"eloRate":595,"eloRank":6705,"country":"us"},"time":695167,"replayExist":true},{"rank":27,"player":{"uuid":"9649236873db4cb9b7bdc2dae693ed39","nickname":"Yosa1003","roleType":0,"eloRate":927,"eloRank":3824,"country":null},"time":740528,"replayExist":true},{"rank":28,"player":{"uuid":"0ddd8edb123d47069d6f8f5aa594b2a3","nickname":"Jakekub","roleType":0,"eloRate":1149,"eloRank":1992,"country":"us"},"time":752399,"replayExist":true},{"rank":29,"player":{"uuid":"b0f46207e362465ba0eb1d364836a13a","nickname":"riaodn","roleType":0,"eloRate":null,"eloRank":null,"country":null},"time":766489,"replayExist":true},{"rank":30,"player":{"uuid":"67587b8c25544bfe95b7f712a2cc0d29","nickname":"Snubagaff","roleType":0,"eloRate":1054,"eloRank":2719,"country":null},"time":772453,"replayExist":true},{"rank":31,"player":{"uuid":"9cd4ea4adfdd48469b35f017102a92c2","nickname":"FlyLikeOstrich","roleType":0,"eloRate":null,"eloRank":null,"country":"ca"},"time":812472,"replayExist":true},{"rank":32,"player":{"uuid":"3dd7c6211e6e4217b3f3985a96122ffb","nickname":"JonaxayyYT","roleType":3,"eloRate":744,"eloRank":5211,"country":"dk"},"time":880289,"replayExist":true},{"rank":33,"player":{"uuid":"e776ad143fe64d3283021496c19eea40","nickname":"TeddyCyborg","roleType":0,"eloRate":null,"eloRank":null,"country":null},"time":963009,"replayExist":true},{"rank":34,"player":{"uuid":"61e32a890b464016bdf7a2b543f4a765","nickname":"WookiesRPpl2_","roleType":0,"eloRate":null,"eloRank":null,"country":null},"time":1058172,"replayExist":true},{"rank":35,"player":{"uuid":"d3f61c13b0a045d6942e5c3f229c066b","nickname":"Deh123123","roleType":0,"eloRate":null,"eloRank":null,"country":null},"time":1186449,"replayExist":true},{"rank":36,"player":{"uuid":"d9c678bf811c49caa8285cbba491840f","nickname":"Luscapitokinha","roleType":0,"eloRate":694,"eloRank":5656,"country":null},"time":1328289,"replayExist":true},{"rank":37,"player":{"uuid":"18bf232f98954470a4ad763c5327aec9","nickname":"uselessleaf","roleType":0,"eloRate":944,"eloRank":3697,"country":"ca"},"time":1389775,"replayExist":true},{"rank":38,"player":{"uuid":"4639c4a765ef4b93b4fd01b7dc23d1a1","nickname":"Throughpond","roleType":0,"eloRate":1138,"eloRank":2080,"country":null},"time":1622788,"replayExist":true},{"rank":39,"player":{"uuid":"ec6d602efb1540e686ed70ed948042dc","nickname":"Hodgeymic","roleType":0,"eloRate":733,"eloRank":5299,"country":null},"time":1698286,"replayExist":true},{"rank":40,"player":{"uuid":"b1c38c8b164649228166c56f207a6e1e","nickname":"Glickky","roleType":0,"eloRate":551,"eloRank":7146,"country":"au"},"time":1949552,"replayExist":true}]}}