{"status":"success","data":{"id":35,"seed":{"overworld":"2386856914173618039","nether":"2386856914173618039","theEnd":"2386856914173618039","rng":"2386856914173618039","flags":72},"endsAt":1748822400,"leaderboard":[{"rank":1,"player":{"uuid":"546e2423a5f94ab9995053bf52045c1f","nickname":"nsla","roleType":0,"eloRate":1343,"eloRank":429,"country":"ua"},"time":124663,"replayExist":true},{"rank":2,"player":{"uuid":"fe6771646c5d43c1b713023fb69c10c6","nickname":"SammmyG","roleType":0,"eloRate":1620,"eloRank":93,"country":"au"},"time":124925,"replayExist":true},{"rank":3,"player":{"uuid":"a20541925b5648e1ae88a141ca37911e","nickname":"xiamoys","roleType":0,"eloRate":null,"eloRank":null,"country":"cn"},"time":128912,"replayExist":true},{"rank":4,"player":{"uuid":"112ed99a4985446a9be1ec43e7b2b618","nickname":"KeimaJirou","roleType":0,"eloRate":1159,"eloRank":1157,"country":"jp"},"time":138889,"replayExist":true},{"rank":5,"player":{"uuid":"4bf064c642dc4937a5b0d9b6327a7119","nickname":"JasGamer409","roleType":0,"eloRate":1330,"eloRank":459,"country":"pl"},"time":139380,"replayExist":true},{"rank":6,"player":{"uuid":"d67b5178a96547ff821ad62e0d3b52dc","nickname":"Apologize_Leaf","roleType":0,"eloRate":null,"eloRank":null,"country":null},"time":140637,"replayExist":true},{"rank":7,"player":{"uuid":"a39bc5337b1341ac974a7952efdc9d4b","nickname":"Sapless","roleType":0,"eloRate":null,"eloRank":null,"country":null},"time":141162,"replayExist":true},{"rank":8,"player":{"uuid":"ca63cf6446c24fa2a1b1396c5a0159eb","nickname":"Aura_Pharmer","roleType":3,"eloRate":1415,"eloRank":277,"country":"us"},"time":141670,"replayExist":true},{"rank":9,"player":{"uuid":"4525d86dfeec4ec1b387f7751a532e46","nickname":"FlaxyB","roleType":0,"eloRate":1309,"eloRank":533,"country":"ca"},"time":142472,"replayExist":true},{"rank":10,"player":{"uuid":"c17e189ba2d4410386d33df98ef75c85","nickname":"Yousa148","roleType":0,"eloRate":null,"eloRank":null,"country":null},"time":143700,"replayExist":true},{"rank":11,"player":{"uuid":"43b352a1ae5948e697f76d7032510d24","nickname":"Sanzione","roleType":0,"eloRate":1238,"eloRank":759,"country":"cn"},"time":144380,"replayExist":true},{"rank":12,"player":{"uuid":"2f6537dae0cd4dc2b456c634194c6d42","nickname":"GakkGakk_","roleType":0,"eloRate":1222,"eloRank":826,"country":"no"},"time":145308,"replayExist":true},{"rank":13,"player":{"uuid":"6044948e096c41cdb3116b3f497762c0","nickname":"Xiaokai_kk","roleType":0,"eloRate":1517,"eloRank":165,"country":"cn"},"time":146973,"replayExist":true},{"rank":14,"player":{"uuid":"a53540ad086c490e9a0405171f0e0e58","nickname":"aleen","roleType":0,"eloRate":1473,"eloRank":212,"country":"ru"},"time":148255,"replayExist":true},{"rank":15,"player":{"uuid":"0ab0ba891f1f4730b570383c00a0286c","nickname":"niki_uu","roleType":0,"eloRate":1049,"eloRank":1904,"country":"ru"},"time":148731,"replayExist":true},{"rank":16,"player":{"uuid":"43ef89d11ec542d1a5b0e58079629059","nickname":"yosimH","roleType":0,"eloRate":null,"eloRank":null,"country":null},"time":149968,"replayExist":true},{"rank":17,"player":{"uuid":"5175370d0a43400e9c5fef63db7aa56e","nickname":"Orion_bo","roleType":1,"eloRate":1224,"eloRank":812,"country":"cn"},"time":152116,"replayExist":true},{"rank":18,"player":{"uuid":"1c4ab40e861a4240b828f37e9a85c9d6","nickname":"nolettuceplz","roleType":1,"eloRate":1206,"eloRank":922,"country":null},"time":153229,"replayExist":true},{"rank":19,"player":{"uuid":"c7207ed672154e84ad02fd5e96865b9a","nickname":"UVZT","roleType":0,"eloRate":959,"eloRank":2680,"country":"us"},"time":154812,"replayExist":true},{"rank":20,"player":{"uuid":"b9019d5a71034e1c80991600482d0577","nickname":"tarakobutterda","roleType":0,"eloRate":722,"eloRank":4522,"country":null},"time":155572,"replayExist":true},{"rank":21,"player":{"uuid":"ef2803a08d72445b9f17df029a3b87ec","nickname":"v099","roleType":0,"eloRate":1058,"eloRank":1825,"country":"gb"},"time":156030,"replayExist":true},{"rank":22,"player":{"uuid":"6bcfc6b4efca45d18cd86337db12cb94","nickname":"Piissii","roleType":1,"eloRate":1369,"eloRank":359,"country":"kr"},"time":156227,"replayExist":true},{"rank":23,"player":{"uuid":"bbc886da1b024739b4b80f1542e9f61d","nickname":"RED_LIME","roleType":3,"eloRate":1151,"eloRank":1209,"country":"kr"},"time":157970,"replayExist":true},{"rank":24,"player":{"uuid":"242b9b1710574dc2ac014b3eec9c0623","nickname":"Auliep","roleType":0,"eloRate":null,"eloRank":null,"country":null},"time":158075,"replayExist":true},{"rank":25,"player":{"uuid":"46c1b412fbe24c09940f835dc85ad674","nickname":"zZoutex","roleType":0,"eloRate":1108,"eloRank":1468,"country":null},"time":158108,"replayExist":true},{"rank":26,"player":{"uuid":"38be701be7204f5287e84ca0427cc921","nickname":"Yeeholly","roleType":0,"eloRate":985,"eloRank":2451,"country":"us"},"time":158232,"replayExist":true},{"rank":27,"player":{"uuid":"4453152fc51f41738526d35db6164818","nickname":"Pakus","roleType":0,"eloRate":1217,"eloRank":860,"country":"td"},"time":159705,"replayExist":true},{"rank":28,"player":{"uuid":"185b039b70284aa9a98850db4ba88e0d","nickname":"ElegantRobin","roleType":1,"eloRate":1549,"eloRank":135,"country":"cn"},"time":159782,"replayExist":true},{"rank":29,"player":{"uuid":"d5f169745c7d42c1aa952e8ac4595c56","nickname":"darkmatter556","roleType":0,"eloRate":927,"eloRank":2968,"country":"us"},"time":159858,"replayExist":true},{"rank":30,"player":{"uuid":"0c7331700bfb42929e5090d63e289b26","nickname":"yoopicul","roleType":0,"eloRate":1086,"eloRank":1620,"country":null},"time":160594,"replayExist":true},{"rank":31,"player":{"uuid":"76d4cdde810b45c0b1cc69f0d9d6c9cb","nickname":"Zo_ZerOs","roleType":0,"eloRate":978,"eloRank":2521,"country":"th"},"time":161337,"replayExist":true},{"rank":32,"player":{"uuid":"87d7efa9ebeb46829542b94847e6aa3b","nickname":"mulLEAF","roleType":0,"eloRate":1236,"eloRank":765,"country":null},"time":161648,"replayExist":true},{"rank":33,"player":{"uuid":"41fb5bfc15674f7ebf6c613962479b5f","nickname":"MCjiuli","roleType":0,"eloRate":1322,"eloRank":485,"country":"cn"},"time":162595,"replayExist":true},{"rank":34,"player":{"uuid":"d347bf9b30de4592acad885603b81728","nickname":"Kemberly","roleType":0,"eloRate":1324,"eloRank":478,"country":null},"time":164263,"replayExist":true},{"rank":35,"player":{"uuid":"492249a499a44d748cb40079de282009","nickname":"king132gg","roleType":0,"eloRate":1204,"eloRank":935,"country":null},"time":165225,"replayExist":true},{"rank":36,"player":{"uuid":"aadf0ba8d1a24e4e87b5648803c9641c","nickname":"Phoenix7_","roleType":0,"eloRate":914,"eloRank":3076,"country":"fr"},"time":165777,"replayExist":true},{"rank":37,"player":{"uuid":"9ee7b2b472be4fd8850501910202dfc8","nickname":"Ninrobo","roleType":0,"eloRate":1248,"eloRank":712,"country":"jp"},"time":166613,"replayExist":true},{"rank":38,"player":{"uuid":"0df1684d92be402bb75a4155b7f7d3e4","nickname":"DECATNEXTDOOR","roleType":0,"eloRate":null,"eloRank":null,"country":"se"},"time":167180,"replayExist":true},{"rank":39,"player":{"uuid":"f0b3663672f945bcaea2bce47c16a300","nickname":"tulnukas4","roleType":0,"eloRate":979,"eloRank":2514,"country":null},"time":167730,"replayExist":true},{"rank":40,"player":{"uuid":"8fbffd3ab2c34ab4af380ccd68c1ae18","nickname":"sanjijia","roleType":1,"eloRate":1157,"eloRank":1171,"country":"cn"},"time":167797,"replayExist":true},{"rank":41,"player":{"uuid":"a5871a0d07b142589b74ec6dd2e7b42b","nickname":"who2661234","roleType":0,"eloRate":258,"eloRank":5335,"country":null},"time":168083,"replayExist":true},{"rank":42,"player":{"uuid":"b2995f32ea7b4d90909805854e1056ea","nickname":"harusameworkd12","roleType":0,"eloRate":1054,"eloRank":1867,"country":null},"time":169310,"replayExist":true},{"rank":43,"player":{"uuid":"6e39b1785cf54f2b95f86dfc6751a8a1","nickname":"SheepAreFine","roleType":0,"eloRate":1031,"eloRank":2069,"country":"no"},"time":169836,"replayExist":true},{"rank":44,"player":{"uuid":"c4ef804f7d154b9798e7941ee28fb894","nickname":"RID3","roleType":0,"eloRate":1228,"eloRank":801,"country":null},"time":170242,"replayExist":true},{"rank":45,"player":{"uuid":"64cd8793f89e4d7481812d59aa03dedc","nickname":"xSpacebar","roleType":0,"eloRate":1025,"eloRank":2123,"country":"no"},"time":170404,"replayExist":true},{"rank":46,"player":{"uuid":"28aea25e0e014ef4844face326eff7a0","nickname":"AtomicTaco99","roleType":0,"eloRate":918,"eloRank":3040,"country":null},"time":170965,"replayExist":true},{"rank":47,"player":{"uuid":"acfd7c3a9db34958afeba9d1b081d3f3","nickname":"TowardStars","roleType":0,"eloRate":1104,"eloRank":1495,"country":"cn"},"time":173803,"replayExist":true},{"rank":48,"player":{"uuid":"a8c9d33cd80249f28e6ecacbc12a4e70","nickname":"ActualCat866","roleType":0,"eloRate":1019,"eloRank":2173,"country":null},"time":174975,"replayExist":true},{"rank":49,"player":{"uuid":"48d9df3377554043ba39a8500c7ad702","nickname":"tenes49","roleType":1,"eloRate":1701,"eloRank":49,"country":"cn"},"time":176638,"replayExist":true},{"rank":50,"player":{"uuid":"fdcbd738ce1b4df5829d56f9a0758d57","nickname":"HaydCarterPookie","roleType":0,"eloRate":1042,"eloRank":1961,"country":"ca"},"time":178253,"replayExist":true}]}}