{"status":"success","data":{"id":68,"seed":{"overworld":"683314300694637541","nether":"683314300694637541","theEnd":"683314300694637541","rng":"683314300694637541","flags":null},"endsAt":1768780800,"leaderboard":[{"rank":1,"player":{"uuid":"fe6771646c5d43c1b713023fb69c10c6","nickname":"SammmyG","roleType":0,"eloRate":1824,"eloRank":30,"country":"au"},"time":280803,"replayExist":true},{"rank":2,"player":{"uuid":"a20541925b5648e1ae88a141ca37911e","nickname":"xiamoys","roleType":0,"eloRate":null,"eloRank":null,"country":"cn"},"time":307693,"replayExist":true},{"rank":3,"player":{"uuid":"43b352a1ae5948e697f76d7032510d24","nickname":"sanzione","roleType":0,"eloRate":1202,"eloRank":1760,"country":"cn"},"time":379857,"replayExist":true},{"rank":4,"player":{"uuid":"8507cf4826da41c7b5ce1f2571257498","nickname":"ItsCap","roleType":1,"eloRate":1227,"eloRank":1460,"country":"gb"},"time":428354,"replayExist":true},{"rank":5,"player":{"uuid":"8f72126108994211820020a8ada9659e","nickname":"uhbysal","roleType":2,"eloRate":1023,"eloRank":3900,"country":"ca"},"time":487746,"replayExist":true},{"rank":6,"player":{"uuid":"156630ba9e474edcbde8ea1334896a77","nickname":"Maxon42055","roleType":0,"eloRate":null,"eloRank":null,"country":null},"time":499117,"replayExist":true},{"rank":7,"player":{"uuid":"49f2aa492cec4c228fb7ffd9c39516e0","nickname":"Igelway","roleType":0,"eloRate":null,"eloRank":null,"country":"de"},"time":525350,"replayExist":true},{"rank":8,"player":{"uuid":"f5c8ce4a858d40e5bb02039661d2a174","nickname":"Andyos28","roleType":0,"eloRate":1249,"eloRank":1278,"country":"ec"},"time":547421,"replayExist":true},{"rank":9,"player":{"uuid":"5267750cbfed46e3a40ab17acfbd614f","nickname":"stennu67","roleType":0,"eloRate":1291,"eloRank":1013,"country":"ee"},"time":572420,"replayExist":true},{"rank":10,"player":{"uuid":"6d23a90c101d46748f335638d4400663","nickname":"Mr_Unicornz","roleType":1,"eloRate":1135,"eloRank":2423,"country":null},"time":575317,"replayExist":true},{"rank":11,"player":{"uuid":"1522945053ae4b48b7bce6b2e5f5701e","nickname":"mewfea","roleType":0,"eloRate":1296,"eloRank":990,"country":"is"},"time":585518,"replayExist":true},{"rank":12,"player":{"uuid":"0739eb7b0c6f479ca50ba59db61cbc9e","nickname":"zelario12","roleType":0,"eloRate":1057,"eloRank":3461,"country":null},"time":590501,"replayExist":true},{"rank":13,"player":{"uuid":"51c9a853701d4700bd041ede25260dd0","nickname":"RTDStuart","roleType":1,"eloRate":1285,"eloRank":1040,"country":"us"},"time":616102,"replayExist":true},{"rank":14,"player":{"uuid":"c5c832d32bc84a4ba0dd9f022cfe971b","nickname":"azby101","roleType":0,"eloRate":971,"eloRank":4570,"country":"ca"},"time":630878,"replayExist":true},{"rank":15,"player":{"uuid":"2b5a0c1f5a034004850de4587b402e9b","nickname":"linecow","roleType":3,"eloRate":1203,"eloRank":1743,"country":"kp"},"time":638805,"replayExist":true},{"rank":16,"player":{"uuid":"04cd27316776491d93820565ba17b59c","nickname":"lucas2mason1","roleType":0,"eloRate":1264,"eloRank":1169,"country":"us"},"time":648048,"replayExist":true},{"rank":17,"player":{"uuid":"e826da86ee9f474083baa3e1ce4c5d11","nickname":"flex_010","roleType":0,"eloRate":337,"eloRank":15292,"country":"de"},"time":666882,"replayExist":true},{"rank":18,"player":{"uuid":"17da86c2ebd34c9892e7c7b1bf5a88bb","nickname":"Yes_Its_Will","roleType":1,"eloRate":1200,"eloRank":1786,"country":"au"},"time":676329,"replayExist":true},{"rank":19,"player":{"uuid":"dbcc30e069ab4cfabedf976202c34dd7","nickname":"SleepCxtz","roleType":0,"eloRate":853,"eloRank":5874,"country":null},"time":677899,"replayExist":true},{"rank":20,"player":{"uuid":"c7c8593e1ff3479cb335e6ce2218f6a5","nickname":"Saltytrash1","roleType":0,"eloRate":null,"eloRank":null,"country":null},"time":682927,"replayExist":true},{"rank":21,"player":{"uuid":"703808b01cf241be9a74b005f9271301","nickname":"DovthePog","roleType":0,"eloRate":1296,"eloRank":990,"country":"lt"},"time":697828,"replayExist":true},{"rank":22,"player":{"uuid":"c589edf4790c43ad8d1e3c8a1a4924ce","nickname":"SPYFOX444","roleType":0,"eloRate":null,"eloRank":null,"country":null},"time":719231,"replayExist":true},{"rank":23,"player":{"uuid":"a2db9ef84c35440ea56618587909ba04","nickname":"LordOfTheNoobs11","roleType":0,"eloRate":null,"eloRank":null,"country":null},"time":746777,"replayExist":true},{"rank":24,"player":{"uuid":"42ad880ec0f1489b96cb548849feef08","nickname":"rdaug","roleType":0,"eloRate":894,"eloRank":5506,"country":null},"time":761848,"replayExist":true},{"rank":25,"player":{"uuid":"8d5fe49759924d6b9e4c65525bbda2d0","nickname":"CKLeo2006","roleType":0,"eloRate":1360,"eloRank":680,"country":"ca"},"time":762320,"replayExist":true},{"rank":26,"player":{"uuid":"0cfef09a908c4968a049e5e08ca46425","nickname":"yourepicruler","roleType":0,"eloRate":1101,"eloRank":2885,"country":null},"time":768786,"replayExist":true},{"rank":27,"player":{"uuid":"4ce4c988c2024346b1020fe897dbdd06","nickname":"DFrqn","roleType":0,"eloRate":null,"eloRank":null,"country":null},"time":790808,"replayExist":true},{"rank":28,"player":{"uuid":"5294d1fc89dc4d27af1db0f71f0d387f","nickname":"_telepathy","roleType":0,"eloRate":717,"eloRank":7328,"country":"au"},"time":794427,"replayExist":true},{"rank":29,"player":{"uuid":"a2c943307f7f4f129d306727b7971893","nickname":"SmileyViller","roleType":0,"eloRate":null,"eloRank":null,"country":"us"},"time":794464,"replayExist":true},{"rank":30,"player":{"uuid":"6acead6e455b475c9693a6f48fa6a4d8","nickname":"TVBRUTAL","roleType":1,"eloRate":732,"eloRank":7098,"country":"kr"},"time":799537,"replayExist":true},{"rank":31,"player":{"uuid":"7354434edacb488a80cab7fd2f112845","nickname":"_kaooadggez","roleType":0,"eloRate":null,"eloRank":null,"country":"th"},"time":806044,"replayExist":true},{"rank":32,"player":{"uuid":"b558abe3b2944c179bad9b4c3cd75c33","nickname":"Dilony16","roleType":0,"eloRate":607,"eloRank":9850,"country":null},"time":808559,"replayExist":true},{"rank":33,"player":{"uuid":"2bbf5ee4516049c69014506ba3dc8763","nickname":"JoshuaLalu","roleType":1,"eloRate":801,"eloRank":6344,"country":"ph"},"time":868435,"replayExist":true},{"rank":34,"player":{"uuid":"60eb603f2204467d8925be78a0e6d316","nickname":"Syzm1k","roleType":0,"eloRate":576,"eloRank":10674,"country":null},"time":882113,"replayExist":true},{"rank":35,"player":{"uuid":"99f3144ea75342f884f02e20c4563e59","nickname":"PianoMan733","roleType":0,"eloRate":null,"eloRank":null,"country":"us"},"time":907984,"replayExist":true},{"rank":36,"player":{"uuid":"cad0bc1ede28443e86b4ba907a01ffad","nickname":"SolaceonX","roleType":0,"eloRate":1253,"eloRank":1249,"country":null},"time":938369,"replayExist":true},{"rank":37,"player":{"uuid":"ae281b16320849e3a8ac89720810b7ea","nickname":"Nanfeng_www","roleType":1,"eloRate":null,"eloRank":null,"country":null},"time":940981,"replayExist":true},{"rank":38,"player":{"uuid":"3a0e6c20c3cf44c6ac6d39cb1e1a4c76","nickname":"ubindy","roleType":0,"eloRate":1174,"eloRank":1982,"country":"us"},"time":943524,"replayExist":true},{"rank":39,"player":{"uuid":"91e87cb40b0444e496f49dfe97af2c0b","nickname":"Bombsan","roleType":0,"eloRate":846,"eloRank":5934,"country":"au"},"time":952115,"replayExist":true},{"rank":40,"player":{"uuid":"504dc16fa66f486391f86f1462b40fe0","nickname":"GangtaPepe","roleType":0,"eloRate":null,"eloRank":null,"country":null},"time":960675,"replayExist":true},{"rank":41,"player":{"uuid":"7166311538744d8dbb8e5fbf0447ffbd","nickname":"saamm1","roleType":0,"eloRate":1105,"eloRank":2830,"country":null},"time":962543,"replayExist":true},{"rank":42,"player":{"uuid":"0749ff28a0604468954d56c921b25970","nickname":"KhungLonggDN","roleType":0,"eloRate":null,"eloRank":null,"country":null},"time":985409,"replayExist":true},{"rank":43,"player":{"uuid":"1c8eef3dc0364e8081b84bb4f436b82a","nickname":"Rounduction","roleType":0,"eloRate":1130,"eloRank":2488,"country":"hr"},"time":1025805,"replayExist":true},{"rank":44,"player":{"uuid":"cdaa52e66cf746ca8826586a23e3451d","nickname":"ShirtlessGuy07","roleType":0,"eloRate":1015,"eloRank":4009,"country":null},"time":1034742,"replayExist":true},{"rank":45,"player":{"uuid":"67403e2f87fd403eabacba1e4ce2f21c","nickname":"WhoopiG710","roleType":0,"eloRate":780,"eloRank":6544,"country":"us"},"time":1043594,"replayExist":true},{"rank":46,"player":{"uuid":"6def823039c94c61a6916c6c3fa4baab","nickname":"GEwe0476","roleType":0,"eloRate":718,"eloRank":7315,"country":"jp"},"time":1048018,"replayExist":true},{"rank":47,"player":{"uuid":"f5b302f44eb6490fb68181cf3a34a3f0","nickname":"stargzrr","roleType":0,"eloRate":null,"eloRank":null,"country":"br"},"time":1070624,"replayExist":true},{"rank":48,"player":{"uuid":"2c2a294f93f344efb5cf62c8ebf24bea","nickname":"lameiradk","roleType":0,"eloRate":689,"eloRank":7815,"country":"br"},"time":1071364,"replayExist":true},{"rank":49,"player":{"uuid":"2ec8a76435274a45a681230cb9f6dccd","nickname":"SkylerGW","roleType":0,"eloRate":812,"eloRank":6230,"country":null},"time":1095063,"replayExist":true},{"rank":50,"player":{"uuid":"427473e5ce9c43d9b5bf68efae42d3c3","nickname":"0ntro","roleType":0,"eloRate":null,"eloRank":null,"country":"cz"},"time":1111965,"replayExist":true}]}}