{"status":"success","data":{"id":51,"seed":{"overworld":"1046431365033868365","nether":"1046431365033868365","theEnd":"1046431365033868365","rng":"1046431365033868365","flags":null},"endsAt":1758499200,"leaderboard":[{"rank":1,"player":{"uuid":"6f090320e9a14aaa8560c2fb8f65faaf","nickname":"BaddiePiglin","roleType":1,"eloRate":1212,"eloRank":1200,"country":null},"time":438528,"replayExist":true},{"rank":2,"player":{"uuid":"06208899940646f58baba4f37c335b03","nickname":"JaronWQHD","roleType":2,"eloRate":1228,"eloRank":1095,"country":"de"},"time":492050,"replayExist":true},{"rank":3,"player":{"uuid":"badc2d085dcd443fbe9757681ec46803","nickname":"LucasBort","roleType":0,"eloRate":958,"eloRank":2585,"country":"br"},"time":512751,"replayExist":true},{"rank":4,"player":{"uuid":"f5f107d2820c4fc49ae16f317a10189f","nickname":"seri_15","roleType":1,"eloRate":1478,"eloRank":309,"country":"jp"},"time":515027,"replayExist":true},{"rank":5,"player":{"uuid":"5cbfeeaa84514606899e7b9d9fa46df4","nickname":"TWsteve05","roleType":0,"eloRate":null,"eloRank":null,"country":null},"time":554621,"replayExist":true},{"rank":6,"player":{"uuid":"d5f169745c7d42c1aa952e8ac4595c56","nickname":"darkmatter556","roleType":0,"eloRate":887,"eloRank":2884,"country":"us"},"time":608045,"replayExist":true},{"rank":7,"player":{"uuid":"5a8576d3989449069a5a42434c8d3351","nickname":"jingjuDcrh2e","roleType":0,"eloRate":577,"eloRank":4130,"country":null},"time":1326393,"replayExist":true}]}}